ovinc_client/__init__.py
ovinc_client/client.py
ovinc_client/constants.py
ovinc_client/account/__init__.py
ovinc_client/account/admin.py
ovinc_client/account/apps.py
ovinc_client/account/constants.py
ovinc_client/account/exceptions.py
ovinc_client/account/models.py
ovinc_client/account/serializers.py
ovinc_client/account/signals.py
ovinc_client/account/urls.py
ovinc_client/account/views.py
ovinc_client/account/migrations/0001_initial.py
ovinc_client/account/migrations/0002_usertoken.py
ovinc_client/account/migrations/0003_rename_usertoken_user_expired_at_account_use_user_id_d3f0e3_idx_and_more.py
ovinc_client/account/migrations/__init__.py
ovinc_client/components/__init__.py
ovinc_client/components/auth.py
ovinc_client/components/base.py
ovinc_client/components/notice.py
ovinc_client/core/__init__.py
ovinc_client/core/auth.py
ovinc_client/core/cache.py
ovinc_client/core/constants.py
ovinc_client/core/exceptions.py
ovinc_client/core/lock.py
ovinc_client/core/logger.py
ovinc_client/core/middlewares.py
ovinc_client/core/mock.py
ovinc_client/core/models.py
ovinc_client/core/paginations.py
ovinc_client/core/renderers.py
ovinc_client/core/utils.py
ovinc_client/core/viewsets.py
ovinc_client/locale/zh_Hans/LC_MESSAGES/django.mo
ovinc_client/locale/zh_Hans/LC_MESSAGES/django.po
ovinc_client/tcaptcha/__init__.py
ovinc_client/tcaptcha/apps.py
ovinc_client/tcaptcha/constants.py
ovinc_client/tcaptcha/exceptions.py
ovinc_client/tcaptcha/urls.py
ovinc_client/tcaptcha/utils.py
ovinc_client/tcaptcha/views.py
ovinc_client/trace/__init__.py
ovinc_client/trace/apps.py
ovinc_client/trace/constants.py
ovinc_client/trace/exporters.py
ovinc_client/trace/instrumentors.py
ovinc_client/trace/setup.py
ovinc_client/trace/urls.py
ovinc_client/trace/utils.py
ovinc_client/trace/views.py
ovinc_client-0.4.6.dist-info/licenses/LICENSE
ovinc_client-0.4.6.dist-info/METADATA
ovinc_client-0.4.6.dist-info/WHEEL
ovinc_client-0.4.6.dist-info/top_level.txt
ovinc_client-0.4.6.dist-info/RECORD
