Metadata-Version: 2.4
Name: ovinc_client
Version: 0.4.6
Summary: A Tool for OVINC Union API
Home-page: https://www.ovinc.cn/
Author: OVINC
Author-email: contact@ovinc.cn
Requires-Python: >=3.12
License-File: LICENSE
Requires-Dist: django<6,>=5.2
Requires-Dist: django_environ<1,>=0.10.0
Requires-Dist: djangorestframework<4,>=3.14.0
Requires-Dist: pymysql<2,>=1
Requires-Dist: django-cors-headers<5,>=4.6.0
Requires-Dist: pytz<2026,>=2022.4
Requires-Dist: django-sslserver<1,>=0.22
Requires-Dist: pyOpenSSL<26,>=22.1.0
Requires-Dist: django-simpleui<2026,>=2023.8.28
Requires-Dist: channels<5,>=4
Requires-Dist: redis<6,>=5.0.0
Requires-Dist: django-redis<6,>=5.0.0
Requires-Dist: python_json_logger<3,>=2.0.3
Requires-Dist: httpx[http2]<1,>=0.23.2
Requires-Dist: requests<3,>=2.32.0
Requires-Dist: urllib3<3,>=2.6.3
Requires-Dist: protobuf<7,>=6.33.4
Requires-Dist: opentelemetry-api==1.39.1
Requires-Dist: opentelemetry-sdk==1.39.1
Requires-Dist: opentelemetry-exporter-otlp==1.39.1
Requires-Dist: opentelemetry-instrumentation==0.60b1
Requires-Dist: opentelemetry-instrumentation-asgi==0.60b1
Requires-Dist: opentelemetry-instrumentation-django==0.60b1
Requires-Dist: opentelemetry-instrumentation-dbapi==0.60b1
Requires-Dist: opentelemetry-instrumentation-pymysql==0.60b1
Requires-Dist: opentelemetry-instrumentation-redis==0.60b1
Requires-Dist: opentelemetry-instrumentation-requests==0.60b1
Requires-Dist: opentelemetry-instrumentation-celery==0.60b1
Requires-Dist: opentelemetry-instrumentation-logging==0.60b1
Requires-Dist: opentelemetry-instrumentation-httpx==0.60b1
Requires-Dist: ipython<9,>=8.10.0
Requires-Dist: tencentcloud-sdk-python<4,>=3.0.785
Requires-Dist: pycryptodome<4,>=3.20.0
Requires-Dist: pydantic<3,>=2
Dynamic: author
Dynamic: author-email
Dynamic: description
Dynamic: description-content-type
Dynamic: home-page
Dynamic: license-file
Dynamic: requires-dist
Dynamic: requires-python
Dynamic: summary
